compute_mcp_service/__init__.py
compute_mcp_service/__main__.py
compute_mcp_service/server.py
handy_compute_mcp-0.1.5.dist-info/METADATA
handy_compute_mcp-0.1.5.dist-info/WHEEL
handy_compute_mcp-0.1.5.dist-info/entry_points.txt
handy_compute_mcp-0.1.5.dist-info/RECORD
